{"people": [
		{"id":1,"name":"Kazimierz","surname":"Chyclak","birthDate":"1941-02-14","deathDate":"2011-08-26","tombId":121,"sex":"M"},
		{"id":2,"name":"Władysława","surname":"Salamon","birthDate":"1935-12-18","deathDate":"2013-05-05","tombId":126,"sex":"K"},
		{"id":3,"name":"Jan","surname":"Salamon","birthDate":"1932-05-05","deathDate":"2014-07-22","tombId":126,"sex":"M"},
		{"id":4,"name":"Józef","surname":"Rzegocki","birthDate":"1947-02-21","deathDate":"2005-12-15","tombId":101,"sex":"M"},
		{"id":5,"name":"Stanisław","surname":"Jurczak","birthDate":"1943-09-29","deathDate":"2013-11-23","tombId":102,"sex":"M"},
		{"id":6,"name":"Joanna","surname":"Rzegocka","birthDate":"1912-11-01","deathDate":"2007-06-12","tombId":101,"sex":"K"},
		{"id":7,"name":"Stanisław","surname":"Nieć","birthDate":"1958-11-04","deathDate":"2005-08-26","tombId":103,"sex":"M"},
		{"id":8,"name":"Józef","surname":"Nieć","birthDate":"1957-06-28","deathDate":"2009-07-19","tombId":103,"sex":"M"},
		{"id":9,"name":"Józef","surname":"Chronowski","birthDate":"1933-08-26","deathDate":"2004-05-02","tombId":104,"sex":"M"},
		{"id":10,"name":"Jan","surname":"Mordarski","birthDate":"1912-04-07","deathDate":"1974-04-23","tombId":117,"sex":"M"},
		{"id":11,"name":"Genowefa","surname":"Mordarska","birthDate":"1923-03-10","deathDate":"2008-04-14","tombId":117,"sex":"K"},
		{"id":12,"name":"Eugeniusz","surname":"Gargula","birthDate":"1926-10-07","deathDate":"2011-12-05","tombId":116,"sex":"M"},
		{"id":13,"name":"Władysława","surname":"Gargula","birthDate":"1928-06-17","deathDate":"2014-06-14","tombId":116,"sex":"K"},
		{"id":14,"name":"Jan","surname":"Bugajski","birthDate":"1957-06-18","deathDate":"2008-10-26","tombId":115,"sex":"M"},
		{"id":15,"name":"Bogdan","surname":"Świderski","birthDate":"1971-07-07","deathDate":"2011-12-23","tombId":119,"sex":"M"},
		{"id":16,"name":"Franciszek","surname":"Krupa","birthDate":"1943-04-01","deathDate":"2013-12-30","tombId":125,"sex":"M"},
		{"id":17,"name":"Piotr","surname":"Chronowski","birthDate":"1979-03-15","deathDate":"2007-01-13","tombId":105,"sex":"M"},
		{"id":18,"name":"Marian","surname":"Janik","birthDate":"1960","deathDate":"2008","tombId":106,"sex":"M"},
		{"id":19,"name":"Wanda","surname":"Witowska","birthDate":"1947-07-21","deathDate":"2006-01-30","tombId":107,"sex":"K"},
		{"id":20,"name":"Władysław","surname":"Janik","birthDate":"1932-04-25","deathDate":"2012-06-30","tombId":108,"sex":"M"},
		{"id":21,"name":"Stanisława","surname":"Janik","birthDate":"1935-03-13","deathDate":"2016-12-27","tombId":108,"sex":"K"},
		{"id":22,"name":"Jan","surname":"Rzegocki","birthDate":"1935-08-19","deathDate":"2015-10-01","tombId":109,"sex":"M"},
		{"id":23,"name":"Helena","surname":"Rzegocka","birthDate":"1935-05-09","deathDate":"2018-04-23","tombId":109,"sex":"K"},
		{"id":24,"name":"Jan","surname":"Węgrzyn","birthDate":"1929-11-28","deathDate":"2007-02-26","tombId":110,"sex":"M"},
		{"id":25,"name":"Tadeusz","surname":"Edelmuller","birthDate":"1943","deathDate":"2007","tombId":111,"sex":"M"},
		{"id":26,"name":"Jadwiga","surname":"Sądelska","birthDate":"1957-10-12","deathDate":"2007-07-28","tombId":112,"sex":"K"},
		{"id":27,"name":"Zygmunt","surname":"Gucwa","birthDate":"1932-12-12","deathDate":"2006-11-30","tombId":113,"sex":"M"},
		{"id":28,"name":"Stefania","surname":"Gucwa","birthDate":"1932-06-26","deathDate":"2000-02-21","tombId":113,"sex":"K"},
		{"id":29,"name":"Zdzisław","surname":"Oleksy","birthDate":"1952-11-15","deathDate":"2012-06-28","tombId":118,"sex":"M"},
		{"id":30,"name":"Stanisław","surname":"Plata","birthDate":"1943-10-26","deathDate":"2014-03-23","tombId":122,"sex":"M"},
		{"id":31,"name":"Józefa Anna","surname":"Korona","birthDate":"1952-03-13","deathDate":"2015-10-04","tombId":123,"sex":"K"},
		{"id":32,"name":"Anna","surname":"Pajor","birthDate":"1966-01-19","deathDate":"2014-03-28","tombId":132,"sex":"K"},
		{"id":33,"name":"Edyta","surname":"Górowska","birthDate":"1996-01-06","deathDate":"2015-07-23","tombId":133,"sex":"K"},
		{"id":34,"name":"Ania","surname":"Ledniowska","birthDate":"1982-09-11","deathDate":"1982-09-11","tombId":134,"sex":"K"},
		{"id":35,"name":"Mieczysława","surname":"Ledniowska","birthDate":"1951-01-02","deathDate":"2017-07-06","tombId":134,"sex":"K"},
		{"id":36,"name":"Halina","surname":"Szczygieł","birthDate":"1947-05-15","deathDate":"2015-04-28","tombId":135,"sex":"K"},
		{"id":37,"name":"Adaś","surname":"Michalik","birthDate":"1986-12-21","deathDate":"1987-02-10","tombId":136,"sex":"M"},
		{"id":38,"name":"Stanisław","surname":"Węgrzyn","birthDate":"1961-11-18","deathDate":"2014-09-01","tombId":127,"sex":"M"},
		{"id":39,"name":"Mateusz","surname":"Fałowski","birthDate":"1968-07-23","deathDate":"2014-11-28","tombId":128,"sex":"M"},
		{"id":40,"name":"Anna Franciszka","surname":"Leśniak","birthDate":"1948-03-16","deathDate":"2015-09-16","tombId":129,"sex":"K"},
		{"id":41,"name":"Elżbieta","surname":"Leśniak","birthDate":"1948-11-01","deathDate":"2013-09-22","tombId":130,"sex":"K"},
		{"id":42,"name":"Józef","surname":"Płachta","birthDate":"1956-10-09","deathDate":"2018-01-07","tombId":131,"sex":"M"},
		{"id":43,"name":"Anna","surname":"Zabrzańska","birthDate":"1923-07-22","deathDate":"1998-08-20","tombId":131,"sex":"K"},
		{"id":44,"name":"Kazimierz","surname":"Zabrzański","birthDate":"1926-04-01","deathDate":"2012-12-02","tombId":131,"sex":"M"},
		{"id":45,"name":"Zofia","surname":"Leśniak","birthDate":"1933-02-17","deathDate":"2018-06-22","tombId":143,"sex":"K"},
		{"id":46,"name":"Bolesław","surname":"Bodziony","birthDate":"1923-05-01","deathDate":"1977-08-31","tombId":144,"sex":"M"},
		{"id":47,"name":"Aniela","surname":"Bodziony","birthDate":"1928-10-20","deathDate":"2014-10-15","tombId":144,"sex":"K"},
		{"id":48,"name":"Jan","surname":"Litzenberger","birthDate":"1907-06-19","deathDate":"1962-09-10","tombId":146,"sex":"M"},
		{"id":49,"name":"Adam","surname":"Hatlaś","birthDate":"1953-01-01","deathDate":"1967-06-20","tombId":147,"sex":"M"},
		{"id":50,"name":"Genowefa","surname":"Kucia","birthDate":"1927-12-05","deathDate":"1998-11-11","tombId":148,"sex":"K"},
		{"id":51,"name":"Jan","surname":"Głuc","birthDate":"1939-06-12","deathDate":"2018-07-19","tombId":138,"sex":"M"},
		{"id":52,"name":"Halina","surname":"Zaryczyny","birthDate":"1967-02-03","deathDate":"2017-06-15","tombId":139,"sex":"K"},
		{"id":53,"name":"Małgorzata","surname":"Kiełbasa","birthDate":"1979-08-13","deathDate":"2017-01-05","tombId":140,"sex":"K"},
		{"id":54,"name":"Robert","surname":"Kiełbasa","birthDate":"1980-11-21","deathDate":"2017-01-05","tombId":140,"sex":"M"},
		{"id":55,"name":"Teresa","surname":"Świderska","birthDate":"1965-08-13","deathDate":"2016-03-03","tombId":141,"sex":"K"},
		{"id":56,"name":"Krystyna","surname":"Śliwa","birthDate":"1952-08-24","deathDate":"2015-12-19","tombId":142,"sex":"K"},
	
		{"id":57,"name":"Zofia","surname":"Leśniak","birthDate":"1933-02-17","deathDate":"2018-06-22","tombId":201,"sex":"K"},
		{"id":58,"name":"Bolesław","surname":"Bodziony","birthDate":"1923-05-01","deathDate":"1977-08-31","tombId":202,"sex":"M"},
		{"id":59,"name":"Aniela","surname":"Bodziony","birthDate":"1928-10-20","deathDate":"2014-11-15","tombId":202,"sex":"K"},
		{"id":60,"name":"Jan","surname":"Litzenberger","birthDate":"1907-06-19","deathDate":"1962-09-10","tombId":204,"sex":"M"},	
		{"id":61,"name":"Janina","surname":"Litzenberger","birthDate":"1923-12-20","deathDate":"2000-06-25","tombId":204,"sex":"M"},
		{"id":62,"name":"Adam","surname":"Hatlaś","birthDate":"1953","deathDate":"1967-06-20","tombId":205,"sex":"M"},
		{"id":63,"name":"Stefania","surname":"Hatlaś","birthDate":"1912","deathDate":"1975-08-15","tombId":205,"sex":"K"},
		{"id":64,"name":"Józef","surname":"Hatlaś","birthDate":"1918-02-02","deathDate":"2000-11-22","tombId":205,"sex":"M"},
		{"id":65,"name":"Genowefa","surname":"Kucia","birthDate":"1927-12-05","deathDate":"1998-11-11","tombId":206,"sex":"K"},
		{"id":66,"name":"Mikołaj","surname":"Kucia","birthDate":"-","deathDate":"przeżył 76 lat","tombId":206,"sex":"M"},
		{"id":67,"name":"Jan","surname":"Hamiga","birthDate":"1902-06-21","deathDate":"1979-04-25","tombId":207,"sex":"M"},
		{"id":68,"name":"Stefania","surname":"Hamiga","birthDate":"1906-01-01","deathDate":"2001-08-09","tombId":207,"sex":"K"},
		{"id":69,"name":"Józef","surname":"Nieć","birthDate":"1925-05-09","deathDate":"2001-05-27","tombId":208,"sex":"M"},
		{"id":70,"name":"Zofia","surname":"Nieć","birthDate":"1930-12-17","deathDate":"2005-12-01","tombId":208,"sex":"K"},
		{"id":71,"name":"Maria","surname":"Zygmunt","birthDate":"1924-03-27","deathDate":"2004-02-23","tombId":209,"sex":"K"},
		{"id":72,"name":"Franciszek","surname":"Zygmunt","birthDate":"1933-04-11","deathDate":"2012-01-21","tombId":209,"sex":"M"},
		{"id":73,"name":"Michał","surname":"Krupa","birthDate":"1940-04-11","deathDate":"2011-03-30","tombId":210,"sex":"M"},
		{"id":74,"name":"Zofia Franciszka","surname":"Świerczek","birthDate":"1947-10-04","deathDate":"2003-09-22","tombId":211,"sex":"K"},
		{"id":75,"name":"Klaudia","surname":"Jawor","birthDate":"2004-05-27","deathDate":"2007-01-24","tombId":211,"sex":"K"},
		{"id":76,"name":"Józef","surname":"Świerczek","birthDate":"1949-02-02","deathDate":"2011-01-31","tombId":211,"sex":"M"},
		{"id":77,"name":"Michał","surname":"Oleksy","birthDate":"1926-09-01","deathDate":"2008-06-04","tombId":212,"sex":"M"},
		{"id":78,"name":"Stanisława","surname":"Oleksy","birthDate":"1930-03-19","deathDate":"2018-08-22","tombId":212,"sex":"K"},
		{"id":79,"name":"Franciszek","surname":"Dłubacz","birthDate":"1911-05-04","deathDate":"2001-09-09","tombId":213,"sex":"M"},
		{"id":80,"name":"Maria","surname":"Dłubacz","birthDate":"1931-12-15","deathDate":"2011-10-24","tombId":213,"sex":"K"},
		
		{"id":81,"name":"Kunegunda","surname":"Wnęk","birthDate":"1910","deathDate":"2002-09-25","tombId":214,"sex":"K"},
		{"id":82,"name":"Jerzy","surname":"Pasiut","birthDate":"1966-06-30","deathDate":"2005-03-01","tombId":215,"sex":"M"},
		{"id":83,"name":"Jarosław","surname":"Totoś","birthDate":"1994","deathDate":"2003-01-03","tombId":216,"sex":"M"},
		{"id":84,"name":"Eugenia","surname":"Smaga","birthDate":"1923-09-25","deathDate":"2005-07-27","tombId":217,"sex":"K"},
		
		{"id":85,"name":"Maria","surname":"Szneider","birthDate":"1946-05-18","deathDate":"2008-02-22","tombId":219,"sex":"K"},
		
		{"id":86,"name":"Kundegunda","surname":"Krupa","birthDate":"1906-12-21","deathDate":"1972-01-16","tombId":220,"sex":"K"},
		{"id":87,"name":"Michał","surname":"Krupa","birthDate":"1905-05-05","deathDate":"1982-05-02","tombId":220,"sex":"M"},
		{"id":88,"name":"Stanisława","surname":"Krupa","birthDate":"1938-09-19","deathDate":"1992-12-24","tombId":220,"sex":"K"},
		{"id":89,"name":"Józef","surname":"Krupa","birthDate":"1934-11-23","deathDate":"2002-12-23","tombId":220,"sex":"M"},
		{"id":90,"name":"Genowefa","surname":"Podmańska","birthDate":"1931-04-04","deathDate":"2013-12-27","tombId":220,"sex":"K"},
		{"id":91,"name":"Maria","surname":"Ruchała","birthDate":"1931-10-25","deathDate":"2009-10-26","tombId":221,"sex":"K"},
		{"id":92,"name":"Andrzej","surname":"Cabała","birthDate":"1941-11-25","deathDate":"2010-09-08","tombId":223,"sex":"M"},
		{"id":93,"name":"Józef","surname":"Liber","birthDate":"1938-10-05","deathDate":"2018-03-16","tombId":224,"sex":"M"},
		{"id":94,"name":"Maria","surname":"Plata","birthDate":"1937-08-02","deathDate":"2018-05-02","tombId":226,"sex":"K"},
		
		{"id":95,"name":"Józef","surname":"Tyrkiel","birthDate":"1918-10-13","deathDate":"1993-02-14","tombId":302,"sex":"M"},
		{"id":96,"name":"Katarzyna","surname":"Tyrkiel","birthDate":"1914-09-13","deathDate":"1996-01-16","tombId":302,"sex":"K"},
		{"id":97,"name":"Justynka","surname":"Kudynowska","birthDate":"2000-03-08","deathDate":"2000-04-10","tombId":302,"sex":"K"},
		
		{"id":98,"name":"Józef","surname":"Kasprzyk","birthDate":"1898-01-14","deathDate":"1986-01-27","tombId":303,"sex":"M"},
		{"id":99,"name":"Rozalia","surname":"Kasprzyk","birthDate":"1895-02-12","deathDate":"1952-02-15","tombId":303,"sex":"K"},
		{"id":100,"name":"Franciszek","surname":"Kasprzyk","birthDate":"1938-10-01","deathDate":"2002-02-02","tombId":303,"sex":"M"},
		
		{"id":101,"name":"Bolesław","surname":"Świderski","birthDate":"1913","deathDate":"1985-02-22","tombId":304,"sex":"M"},
		{"id":102,"name":"Jan","surname":"Świderski","birthDate":"1949","deathDate":"2003-12-20","tombId":304,"sex":"M"},
		{"id":103,"name":"Wiktoria","surname":"Świderska","birthDate":"1919","deathDate":"2005-12-06","tombId":304,"sex":"K"},
		{"id":104,"name":"Zdzisław","surname":"Pietruszka","birthDate":"1944","deathDate":"1979-12-05","tombId":304,"sex":"M"},
		{"id":105,"name":"Michał","surname":"Baniak","birthDate":"1937-09-05","deathDate":"1985-02-16","tombId":305,"sex":"M"},
		
		{"id":106,"name":"Andrzej","surname":"Lorek","birthDate":"1960-11-26","deathDate":"1986-11-27","tombId":306,"sex":"M"},
		{"id":107,"name":"Władysław","surname":"Lorek","birthDate":"1916-10-20","deathDate":"1989","tombId":306,"sex":"M"},
		{"id":108,"name":"Genowefa","surname":"Lorek","birthDate":"1923-01-26","deathDate":"2004-10-09","tombId":306,"sex":"K"},
		
		{"id":109,"name":"Zygmunt","surname":"Bułat","birthDate":"21.07.1899","deathDate":"7.06.1969","tombId":307,"sex":"M"},
		{"id":110,"name":"Czesław","surname":"Bułat","birthDate":"2.04.1952","deathDate":"1987","tombId":307,"sex":"M"},
		{"id":111,"name":"Maria","surname":"Bułat","birthDate":"21.12.1907","deathDate":"8.08.1989","tombId":307,"sex":"K"},
		{"id":112,"name":"Janusz","surname":"Bułat","birthDate":"8.07.1982","deathDate":"7.02.2006","tombId":307,"sex":"M"},
		{"id":113,"name":"Bronisława","surname":"Olszyńska","birthDate":"8.04.1913","deathDate":"4.04.1977","tombId":308,"sex":"K"},
		{"id":114,"name":"Władysław","surname":"Olszyński","birthDate":"13.04.1913","deathDate":"2.07.1984","tombId":308,"sex":"M"},
		{"id":115,"name":"Kunegunda","surname":"Szołdrowska","birthDate":"24.05.1913","deathDate":"1.07.1982","tombId":309,"sex":"K"},
		{"id":116,"name":"Stanisław","surname":"Szołdrowski","birthDate":"19.03.1913","deathDate":"29.05.1988","tombId":309,"sex":"M"},
		
		{"id":117,"name":"Karolina","surname":"Nieć","birthDate":"17.06.1898","deathDate":"21.01.1974","tombId":310,"sex":"K"},
		{"id":118,"name":"Józef","surname":"Nieć","birthDate":"26.09.1898","deathDate":"22.11.1989","tombId":310,"sex":"M"},
		{"id":119,"name":"Wnuczek Stanisław","surname":"-","birthDate":"27.10.1975","deathDate":"30.10.1975","tombId":310,"sex":"M"},
		{"id":120,"name":"Prawnuczek Jerzy","surname":"-","birthDate":"-","deathDate":"-","tombId":310,"sex":"M"},
		{"id":121,"name":"Zygmunt Michał","surname":"Laburda","birthDate":"9.02.1952","deathDate":"26.01.1990","tombId":311,"sex":"M"},
		{"id":122,"name":"Franciszek","surname":"Podmański","birthDate":"1.04.1934","deathDate":"4.12.2011","tombId":312,"sex":"M"},
		
		
		
		{"id":123,"name":"Władysław","surname":"Ślęzak","birthDate":"29.03.1905","deathDate":"10.03.1994","tombId":313,"sex":"M"},
		{"id":124,"name":"Stefania","surname":"Ślęzak","birthDate":"19.10.1910","deathDate":"5.08.2002","tombId":313,"sex":"K"},
		{"id":125,"name":"Franciszek","surname":"Saska","birthDate":"9.01.1919","deathDate":"8.11.1981","tombId":314,"sex":"M"},
		{"id":126,"name":"Irena","surname":"Saska","birthDate":"11.06.1925","deathDate":"27.08.2002","tombId":314,"sex":"K"},
		{"id":127,"name":"Stanisława","surname":"Saska","birthDate":"19.04.1949","deathDate":"1.06.2013","tombId":314,"sex":"K"},
		
		{"id":128,"name":"Maria","surname":"Szczurek","birthDate":"13.06.1928","deathDate":"18.12.1998","tombId":315,"sex":"K"},
		{"id":129,"name":"Józef","surname":"Szczurek","birthDate":"19.08.1922","deathDate":"14.03.1995","tombId":315,"sex":"M"},
		{"id":130,"name":"Ania","surname":"Musiał","birthDate":"-","deathDate":"-","tombId":315,"sex":"K"},
		{"id":131,"name":"Filipek","surname":"Musiał","birthDate":"-","deathDate":"-","tombId":315,"sex":"M"},
		
		
		{"id":132,"name":"Antonina","surname":"Berowska","birthDate":"6.01.1923","deathDate":"6.06.1997","tombId":316,"sex":"K"},
		
		{"id":134,"name":"Agnieszka","surname":"Klimczak","birthDate":"19.05.1910","deathDate":"5.11.1993","tombId":317,"sex":"K"},
		{"id":135,"name":"Józef","surname":"Klimczak","birthDate":"23.12.1908","deathDate":"17.05.1990","tombId":317,"sex":"M"},
		{"id":136,"name":"Gabryś","surname":"Klimczak","birthDate":"-","deathDate":"-","tombId":317,"sex":"M"},
		
		{"id":137,"name":"Helena","surname":"Biel","birthDate":"1.09.1930","deathDate":"24.09.1990","tombId":318,"sex":"K"},
		
		{"id":138,"name":"Jan Kazimierz","surname":"Fałowski","birthDate":"1.10.1936","deathDate":"22.03.2003","tombId":319,"sex":"M"},
		{"id":139,"name":"Małgorzata","surname":"Fałowska","birthDate":"17.12.1973","deathDate":"22.11.1987","tombId":319,"sex":"M"},
		

		{"id":140,"name":"Józef","surname":"Mróz","birthDate":"31.08.1906","deathDate":"229.05.1987","tombId":320,"sex":"M"},
		{"id":141,"name":"Rozalia","surname":"Mróz","birthDate":"20.04.1907","deathDate":"17.02.1989","tombId":320,"sex":"K"},
		{"id":142,"name":"Janina","surname":"Mróz","birthDate":"28.06.1929","deathDate":"5.08.2013","tombId":320,"sex":"K"},
		
		
		{"id":143,"name":"Jadwiga","surname":"Jędrzejewska","birthDate":"1990","deathDate":"20.07.1974","tombId":321,"sex":"K"},	
		{"id":144,"name":"Jan","surname":"Jędrzejewski","birthDate":"13.10.1907","deathDate":"26.10.1987","tombId":321,"sex":"M"},
		
		{"id":145,"name":"Kunegunda","surname":"Mróz","birthDate":"15.03.1914","deathDate":"3.07.1984","tombId":322,"sex":"K"},
		{"id":146,"name":"Jan","surname":"Mróz","birthDate":"20.12.1908","deathDate":"19.11.1987","tombId":322,"sex":"M"},
				
		{"id":147,"name":"Franciszek","surname":"Konstanty","birthDate":"15.03.1909","deathDate":"6.12.1987","tombId":323,"sex":"M"},
		{"id":148,"name":"Helena","surname":"Konstanty","birthDate":"19.05.1930","deathDate":"7.04.2017","tombId":323,"sex":"K"},
		
		{"id":149,"name":"Jan","surname":"Twardy","birthDate":"1.11.1926","deathDate":"14.03.1988","tombId":324,"sex":"M"},
		{"id":150,"name":"Kunegunda","surname":"Twardy","birthDate":"24.07.1928","deathDate":"6.01.1988","tombId":324,"sex":"K"},
		{"id":151,"name":"Jonaszek","surname":"Gucwa","birthDate":"13.05.1988","deathDate":"13.05.1988","tombId":324,"sex":"M"},
		
		{"id":152,"name":"Stefania","surname":"Knurowska","birthDate":"6.01.1904","deathDate":"10.01.1972","tombId":325,"sex":"K"},
		{"id":153,"name":"Józef","surname":"Knurowski","birthDate":"15.08.1906","deathDate":"28.01.1988","tombId":325,"sex":"M"},
		
		
		{"id":152,"name":"Józef","surname":"Liber","birthDate":"9.10.1912","deathDate":"4.03.1988","tombId":326,"sex":"M"},
		{"id":153,"name":"Agnieszka","surname":"Liber","birthDate":"25.03.1923","deathDate":"28.03.1997","tombId":326,"sex":"K"}

	]
}
